moncoll2/__init__.py
moncoll2-0.2.0.dist-info/LICENSE
moncoll2-0.2.0.dist-info/WHEEL
moncoll2-0.2.0.dist-info/METADATA
moncoll2-0.2.0.dist-info/RECORD
