Metadata-Version: 2.1
Name: moncoll2
Version: 0.2.0
Summary: 
Home-page: https://github.com/atu4403
Author: atu4403 
Author-email: 73111778+atu4403@users.noreply.github.com
Requires-Python: >=3.8,<4.0
Classifier: Programming Language :: Python :: 3
Classifier: Programming Language :: Python :: 3.8
Classifier: Programming Language :: Python :: 3.9
Requires-Dist: pymongo (>=4.0.1,<5.0.0)
Project-URL: Repository, https://github.com/atu4403/moncoll2
